end2end
end2end/core
