Metadata-Version: 2.1
Name: end2end
Version: 1.2
Summary: Python end two end encryption designed for socket
Home-page: https://www.python.org/sigs/distutils-sig/
Author: Julian Wandhoven
Author-email: jwandhoven@gmail.com
License: MIT
Platform: UNKNOWN
License-File: LICENSE
